File_to/__init__.py
File_to/core.py
file_to-0.1.0.dist-info/METADATA
file_to-0.1.0.dist-info/WHEEL
file_to-0.1.0.dist-info/top_level.txt
file_to-0.1.0.dist-info/RECORD
