Metadata-Version: 2.4
Name: File_To
Version: 0.1.0
Summary: A Python module for file and directory operations
Home-page: 
Author: WusRainy
Author-email: 3644365070@qq.com
Classifier: Programming Language :: Python :: 3
Classifier: License :: OSI Approved :: MIT License
Classifier: Operating System :: OS Independent
Requires-Python: >=3.6
Dynamic: author
Dynamic: author-email
Dynamic: classifier
Dynamic: description
Dynamic: description-content-type
Dynamic: requires-python
Dynamic: summary
